vidur/__init__.py
vidur/_native.cpython-310-x86_64-linux-gnu.so
vidur/_version.py
vidur/logger.py
vidur/main.py
vidur/simulator.py
vidur/version.py
vidur/config/__init__.py
vidur/config/base_fixed_config.py
vidur/config/base_poly_config.py
vidur/config/config.py
vidur/config/device_sku_config.py
vidur/config/flat_dataclass.py
vidur/config/model_config.py
vidur/config/node_sku_config.py
vidur/config/utils.py
vidur/config_optimizer/__init__.py
vidur/config_optimizer/analyzer/__init__.py
vidur/config_optimizer/analyzer/bottleneck_analyzer.py
vidur/config_optimizer/analyzer/bottleneck_cases.py
vidur/config_optimizer/analyzer/constants.py
vidur/config_optimizer/analyzer/generate_pareto_curves.py
vidur/config_optimizer/analyzer/stats_extractor.py
vidur/config_optimizer/analyzer/utils.py
vidur/config_optimizer/analyzer/dashboard/__init__.py
vidur/config_optimizer/analyzer/dashboard/best_config_page.py
vidur/config_optimizer/analyzer/dashboard/config_compare_page.py
vidur/config_optimizer/analyzer/dashboard/cost_analysis_page.py
vidur/config_optimizer/analyzer/dashboard/intro_page.py
vidur/config_optimizer/analyzer/dashboard/main.py
vidur/config_optimizer/analyzer/dashboard/pareto_curve_page.py
vidur/config_optimizer/analyzer/dashboard/search_analysis_page.py
vidur/config_optimizer/analyzer/dashboard/utils.py
vidur/config_optimizer/config_explorer/__init__.py
vidur/config_optimizer/config_explorer/capacity_search.py
vidur/config_optimizer/config_explorer/config_explorer.py
vidur/config_optimizer/config_explorer/main.py
vidur/config_optimizer/config_explorer/ray_utils.py
vidur/config_optimizer/config_explorer/config/__init__.py
vidur/config_optimizer/config_explorer/config/config.py
vidur/entities/__init__.py
vidur/entities/base_entity.py
vidur/entities/batch.py
vidur/entities/batch_stage.py
vidur/entities/cluster.py
vidur/entities/execution_time.py
vidur/entities/kv_parallel_batch.py
vidur/entities/kv_parallel_batch_stage.py
vidur-0.0.26.dist-info/METADATA
vidur-0.0.26.dist-info/WHEEL
vidur-0.0.26.dist-info/entry_points.txt
vidur-0.0.26.dist-info/top_level.txt
vidur-0.0.26.dist-info/RECORD
vidur-0.0.26.dist-info/licenses/LICENSE
