Metadata-Version: 2.4
Name: vidur
Version: 0.0.26
Summary: A LLM inference cluster simulator
Home-page: https://mlsys.org/virtual/2024/poster/2667
Author: Systems for AI Lab, Georgia Tech; Microsoft Corporation
Keywords: Simulator,LLM,Inference,Cluster
Classifier: Programming Language :: Python :: 3.10
Classifier: Programming Language :: Python :: 3.11
Classifier: Programming Language :: Python :: 3.12
Classifier: License :: OSI Approved :: MIT License
Classifier: Topic :: Scientific/Engineering :: Artificial Intelligence
Requires-Python: >=3.10
License-File: LICENSE
Requires-Dist: numpy
Requires-Dist: pandas
Requires-Dist: scikit-learn
Requires-Dist: wandb
Requires-Dist: kaleido
Requires-Dist: ddsketch
Requires-Dist: plotly_express
Requires-Dist: matplotlib
Requires-Dist: seaborn
Requires-Dist: fasteners
Requires-Dist: click
Requires-Dist: huggingface_hub
Requires-Dist: ninja
Requires-Dist: paretoset
Requires-Dist: randomname
Requires-Dist: streamlit
Dynamic: author
Dynamic: classifier
Dynamic: description
Dynamic: description-content-type
Dynamic: home-page
Dynamic: keywords
Dynamic: license-file
Dynamic: requires-dist
Dynamic: requires-python
Dynamic: summary
